mriphysio/__init__.py
mriphysio/ecg.py
mriphysio/physio2bids.py
mriphysio/physiodicom.py
mriphysio-2023.8.8.dist-info/LICENSE
mriphysio-2023.8.8.dist-info/METADATA
mriphysio-2023.8.8.dist-info/WHEEL
mriphysio-2023.8.8.dist-info/entry_points.txt
mriphysio-2023.8.8.dist-info/top_level.txt
mriphysio-2023.8.8.dist-info/RECORD
