Metadata-Version: 2.1
Name: mriphysio
Version: 2023.8.8
Summary: Siemens physiology DICOM and MPCU log conversion
Home-page: https://github.com/jmtyszka/mriphysio
Author: Julian Michael Tyszka
Author-email: jmt@caltech.edu
Project-URL: Bug Reports, https://github.com/jmtyszka/thermalfit/issues
Project-URL: Funding, http://cbic.caltech.edu/
Project-URL: Source, https://github.com/jmtyszka/thermalfit/
Keywords: Siemens CMRR physiology conversion MRI
Classifier: Development Status :: 4 - Beta
Classifier: Intended Audience :: Science/Research
Classifier: Topic :: Scientific/Engineering
Classifier: License :: OSI Approved :: MIT License
Classifier: Programming Language :: Python :: 3.9
Classifier: Programming Language :: Python :: 3.10
Requires-Python: >=3.9, <4
License-File: LICENSE
